spepy/__init__.py
spepy-1.0.dist-info/LICENSE.txt
spepy-1.0.dist-info/METADATA
spepy-1.0.dist-info/WHEEL
spepy-1.0.dist-info/top_level.txt
spepy-1.0.dist-info/RECORD
