Metadata-Version: 2.1
Name: spepy
Version: 1.0
Summary: pywhatkit is a Python library for Sending whatsapp message at certain time, it has several other features too.
Home-page: https://github.com/Ankit404butfound/awesomepy
Author: Ankit Raj Mahapatra
Author-email: ankitrajjitendra816@gmail.com
License: MIT
Download-URL: https://github.com/Ankit404butfound/awesomepy/archive/1.0.tar.gz
Keywords: speak
Platform: UNKNOWN
Classifier: Development Status :: 3 - Alpha
Classifier: Intended Audience :: Developers
Classifier: Topic :: Software Development :: Build Tools
Classifier: License :: OSI Approved :: MIT License
Classifier: Programming Language :: Python :: 3
Classifier: Programming Language :: Python :: 3.4
Classifier: Programming Language :: Python :: 3.5
Classifier: Programming Language :: Python :: 3.6
